.aider.chat.history.md
.editorconfig
.github/FUNDING.yml
.github/agents/new-service.agent.md
.github/copilot-new-service.md
.github/workflows/app-release.yml
.github/workflows/bench-docker.yml
.github/workflows/boost-docker.yml
.gitignore
.scripts/add-project-urls.ts
.scripts/app.ts
.scripts/comment.ts
.scripts/deno.json
.scripts/deno.lock
.scripts/docs-to-app.ts
.scripts/docs.ts
.scripts/fluid.sh
.scripts/inliner.ts
.scripts/nbs.sh
.scripts/promx.sh
.scripts/release.sh
.scripts/scaffold.ts
.scripts/seed-cdi.ts
.scripts/seed-traefik.ts
.scripts/seed.ts
.scripts/terser.sh
.style.yapf
.vscode/settings.json
AGENTS.md
LICENSE
README.md
RELEASE.md
activepieces/.gitignore
activepieces/override.env
agent/.gitignore
agent/Dockerfile
agent/docker/services.d/agent.sh
agent/override.env
agent/requirements.txt
agent/src/agent.py
agent/src/chat.py
agent/src/chat_node.py
agent/src/config.py
agent/src/format.py
agent/src/llm.py
agent/src/log.py
agent/src/main.py
agent/src/tasks/chat_to_goal.py
agent/src/tasks/direct.py
agent/src/tasks/next_step.py
agent/src/tasks/plan.py
agent/src/tasks/refine.py
agentzero/.gitignore
agentzero/override.env
aichat/Dockerfile
aichat/configs/aichat.airllm.yml
aichat/configs/aichat.aphrodite.yml
aichat/configs/aichat.config.yml
aichat/configs/aichat.dify.yml
aichat/configs/aichat.ktransformers.yml
aichat/configs/aichat.litellm.yml
aichat/configs/aichat.llamacpp.yml
aichat/configs/aichat.mistralrs.yml
aichat/configs/aichat.ollama.yml
aichat/configs/aichat.sglang.yml
aichat/configs/aichat.tabbyapi.yml
aichat/configs/aichat.vllm.yml
aichat/override.env
aichat/start_aichat.sh
aider/configs/aider.airllm.yml
aider/configs/aider.aphrodite.yml
aider/configs/aider.config.yml
aider/configs/aider.dify.yml
aider/configs/aider.ktransformers.yml
aider/configs/aider.litellm.yml
aider/configs/aider.llamacpp.yml
aider/configs/aider.mistralrs.yml
aider/configs/aider.ollama.yml
aider/configs/aider.sglang.yml
aider/configs/aider.tabbyapi.yml
aider/configs/aider.vllm.yml
llm_harbor-0.3.34.dist-info/LICENSE
llm_harbor-0.3.34.dist-info/METADATA
llm_harbor-0.3.34.dist-info/WHEEL
llm_harbor-0.3.34.dist-info/entry_points.txt
llm_harbor-0.3.34.dist-info/RECORD
