Metadata-Version: 2.1
Name: llm-harbor
Version: 0.3.34
Summary: Effortlessly run LLM backends, APIs, frontends, and services with one command.
Home-page: https://github.com/av/harbor
License: Apache-2.0
Author: av
Author-email: av@av.codes
Requires-Python: >=3.0.0
Classifier: Environment :: Console
Classifier: License :: OSI Approved :: Apache Software License
Classifier: Programming Language :: Python :: 3
Classifier: Programming Language :: Python :: 3.4
Classifier: Programming Language :: Python :: 3.5
Classifier: Programming Language :: Python :: 3.6
Classifier: Programming Language :: Python :: 3.7
Classifier: Programming Language :: Python :: 3.8
Classifier: Programming Language :: Python :: 3.9
Classifier: Programming Language :: Python :: 3.10
Classifier: Programming Language :: Python :: 3.11
Classifier: Programming Language :: Python :: 3.12
Classifier: Topic :: Scientific/Engineering :: Artificial Intelligence
Classifier: Topic :: Utilities
Project-URL: Documentation, https://github.com/av/harbor/wiki
Project-URL: Repository, https://github.com/av/harbor
